flet_runtime/__init__.py
flet_runtime/app.py
flet_runtime/auth/__init__.py
flet_runtime/auth/authorization.py
flet_runtime/auth/group.py
flet_runtime/auth/oauth_provider.py
flet_runtime/auth/oauth_token.py
flet_runtime/auth/providers/__init__.py
flet_runtime/auth/providers/auth0_oauth_provider.py
flet_runtime/auth/providers/azure_oauth_provider.py
flet_runtime/auth/providers/github_oauth_provider.py
flet_runtime/auth/providers/google_oauth_provider.py
flet_runtime/auth/user.py
flet_runtime/flet_socket_server.py
flet_runtime/security/__init__.py
flet_runtime/uploads.py
flet_runtime/utils/__init__.py
flet_runtime/utils/once.py
flet_runtime/utils/patch_index.py
flet_runtime/version.py
flet_contrib_runtime-2024.12.7.2153.dist-info/METADATA
flet_contrib_runtime-2024.12.7.2153.dist-info/WHEEL
flet_contrib_runtime-2024.12.7.2153.dist-info/RECORD
