Metadata-Version: 2.1
Name: flet-contrib-runtime
Version: 2024.12.7.2153
Summary: Flet Runtime - a base package for Flet desktop and Flet mobile.
License: Apache-2.0
Author: Appveyor Systems Inc.
Author-email: hello@flet.dev
Requires-Python: >=3.8,<4.0
Classifier: License :: OSI Approved :: Apache Software License
Classifier: Programming Language :: Python :: 3
Classifier: Programming Language :: Python :: 3.8
Classifier: Programming Language :: Python :: 3.9
Classifier: Programming Language :: Python :: 3.10
Classifier: Programming Language :: Python :: 3.11
Classifier: Programming Language :: Python :: 3.12
Classifier: Programming Language :: Python :: 3.13
Requires-Dist: flet-contrib-core (==2024.12.07.2153)
Requires-Dist: httpx (>=0,<1)
Requires-Dist: oauthlib (>=3.2.2,<4.0.0)
Project-URL: documentation, https://flet.dev/docs
Project-URL: homepage, https://flet.dev
Project-URL: repository, https://github.com/flet-dev/flet
